MANIFEST.in
README.md
setup.py
predictable_jokes/__init__.py
predictable_jokes/jokes.py
predictable_jokes.egg-info/PKG-INFO
predictable_jokes.egg-info/SOURCES.txt
predictable_jokes.egg-info/dependency_links.txt
predictable_jokes.egg-info/entry_points.txt
predictable_jokes.egg-info/top_level.txt
predictable_jokes/data/jokes.json
tests/__init__.py
tests/test_jokes.py